LICENSE
MANIFEST.in
README.md
requirements.txt
setup.py
econball/__init__.py
econball/__main__.py
econball/args.py
econball/coinbase.py
econball/data.py
econball/efd.py
econball/fred.py
econball/oecd.py
econball/pull.py
econball/yfinance.py
econball.egg-info/PKG-INFO
econball.egg-info/SOURCES.txt
econball.egg-info/dependency_links.txt
econball.egg-info/entry_points.txt
econball.egg-info/not-zip-safe
econball.egg-info/requires.txt
econball.egg-info/top_level.txt
tests/__init__.py