Metadata-Version: 2.1
Name: econball
Version: 0.0.15
Summary: A library for pulling in and normalising economic data.
Home-page: https://github.com/8W9aG/econball
Author: Will Sackfield
Author-email: will.sackfield@gmail.com
License: MIT
Keywords: economics,timeseries
Classifier: License :: OSI Approved :: MIT License
Classifier: Programming Language :: Python :: 3
License-File: LICENSE
Requires-Dist: pandas>=2.2.3
Requires-Dist: pyarrow>=19.0.1
Requires-Dist: fredapi>=0.5.2
Requires-Dist: tqdm>=4.67.1
Requires-Dist: python-dotenv>=1.1.0
Requires-Dist: yfinance>=0.2.61
Requires-Dist: cbhist>=0.0.4
Requires-Dist: beautifulsoup4>=4.13.4
Requires-Dist: lxml>=5.4.0
Requires-Dist: requests-cache>=1.2.1
Requires-Dist: python-dateutil>=2.9.0.post0
Requires-Dist: pandasdmx>=1.10.0
